iterseg/__init__.py
iterseg/_dock_widgets.py
iterseg/_io.py
iterseg/augment.py
iterseg/custom_loss.py
iterseg/helpers.py
iterseg/labels.py
iterseg/metrics.py
iterseg/napari.yaml
iterseg/plots.py
iterseg/predict.py
iterseg/segmentation.py
iterseg/train.py
iterseg/train_io.py
iterseg/training_experiments.py
iterseg/unet.py
iterseg/watershed.py
iterseg/_tests/__init__.py
iterseg/data/232208_161159_plateseg.pt
iterseg-0.3.0.dist-info/LICENSE
iterseg-0.3.0.dist-info/METADATA
iterseg-0.3.0.dist-info/WHEEL
iterseg-0.3.0.dist-info/entry_points.txt
iterseg-0.3.0.dist-info/top_level.txt
iterseg-0.3.0.dist-info/RECORD
