Metadata-Version: 2.1
Name: iterseg
Version: 0.3.0
Summary: napari plugin for iteratively improving unet-watershed segmentation
Home-page: https://github.com/abigailmcgovern/iterseg
Author: Abigail S McGovern & Juan Nunez-Iglesias
Author-email: Abigail.McGovern1@monash.edu
License: BSD-3-Clause
Project-URL: Bug Tracker, https://github.com/abigailmcgovern/iterseg/issues
Project-URL: Documentation, https://github.com/abigailmcgovern/iterseg#README.md
Project-URL: Source Code, https://github.com/abigailmcgovern/iterseg
Project-URL: User Support, https://github.com/abigailmcgovern/iterseg/issues
Classifier: Development Status :: 2 - Pre-Alpha
Classifier: Intended Audience :: Developers
Classifier: Framework :: napari
Classifier: Topic :: Software Development :: Testing
Classifier: Programming Language :: Python
Classifier: Programming Language :: Python :: 3
Classifier: Programming Language :: Python :: 3.9
Classifier: Programming Language :: Python :: 3.10
Classifier: Programming Language :: Python :: 3.11
Classifier: Operating System :: OS Independent
Classifier: License :: OSI Approved :: BSD License
Requires-Python: >=3.7
License-File: LICENSE
Requires-Dist: numpy
Requires-Dist: dask
Requires-Dist: torch
Requires-Dist: scikit-image
Requires-Dist: pandas
Requires-Dist: ome-zarr
Requires-Dist: zarr
Requires-Dist: matplotlib
Requires-Dist: napari
Requires-Dist: umetrix
Requires-Dist: numba
Requires-Dist: scipy
Requires-Dist: seaborn
